pretix_plugin_build/__init__.py
pretix_plugin_build/build.py
pretix_plugin_build-1.0.1.dist-info/METADATA
pretix_plugin_build-1.0.1.dist-info/WHEEL
pretix_plugin_build-1.0.1.dist-info/top_level.txt
pretix_plugin_build-1.0.1.dist-info/RECORD
